whisper_normalizer/__init__.py
whisper_normalizer/_modidx.py
whisper_normalizer/basic.py
whisper_normalizer/core.py
whisper_normalizer/english.py
whisper_normalizer/indic.py
whisper_normalizer/langinfo.py
whisper_normalizer/normalizers/english.json
whisper_normalizer-0.1.11.dist-info/licenses/LICENSE
whisper_normalizer-0.1.11.dist-info/METADATA
whisper_normalizer-0.1.11.dist-info/WHEEL
whisper_normalizer-0.1.11.dist-info/entry_points.txt
whisper_normalizer-0.1.11.dist-info/top_level.txt
whisper_normalizer-0.1.11.dist-info/RECORD
