Metadata-Version: 2.4
Name: whisper_normalizer
Version: 0.1.11
Summary: A python package for whisper normalizer
Home-page: https://github.com/kurianbenoy/whisper_normalizer
Author: kurianbenoy
Author-email: kurian.bkk@gmail.com
License: MIT License
Project-URL: Homepage, https://kurianbenoy.github.io/whisper_normalizer/
Project-URL: Repository, https://github.com/kurianbenoy/whisper_normalizer
Keywords: nbdev jupyter notebook openai whisper normalizer
Classifier: Typing :: Typed
Classifier: Intended Audience :: Developers
Classifier: Programming Language :: Python :: 3.7
Classifier: Programming Language :: Python :: 3.8
Classifier: Programming Language :: Python :: 3.9
Classifier: Programming Language :: Python :: 3.10
Classifier: Programming Language :: Python :: 3.11
Classifier: Programming Language :: Python :: 3.12
Classifier: Operating System :: OS Independent
Classifier: Operating System :: POSIX
Classifier: Operating System :: MacOS
Classifier: Operating System :: POSIX :: Linux
Classifier: Operating System :: Microsoft :: Windows
Classifier: Topic :: Software Development :: Libraries :: Python Modules
Classifier: License :: OSI Approved :: MIT License
Requires-Python: >=3.7
License-File: LICENSE
Requires-Dist: more_itertools
Requires-Dist: regex
Requires-Dist: indic-numtowords
Provides-Extra: dev
Requires-Dist: black; extra == "dev"
Requires-Dist: nbdev; extra == "dev"
Requires-Dist: twine; extra == "dev"
Requires-Dist: ipykernel; extra == "dev"
Dynamic: author
Dynamic: author-email
Dynamic: description
Dynamic: description-content-type
Dynamic: home-page
Dynamic: keywords
Dynamic: license
Dynamic: license-file
Dynamic: provides-extra
Dynamic: requires-dist
Dynamic: requires-python
Dynamic: summary
